fairchem/__init__.py
fairchem_applications-0.0.0b0.dist-info/METADATA
fairchem_applications-0.0.0b0.dist-info/WHEEL
fairchem_applications-0.0.0b0.dist-info/top_level.txt
fairchem_applications-0.0.0b0.dist-info/RECORD
